bibliothek/__init__.py
bibliothek/bibliothek.py
papermc_bibliothek-6.0.1.dist-info/LICENSE
papermc_bibliothek-6.0.1.dist-info/METADATA
papermc_bibliothek-6.0.1.dist-info/WHEEL
papermc_bibliothek-6.0.1.dist-info/RECORD
