Metadata-Version: 2.1
Name: papermc-bibliothek
Version: 6.0.1
Summary: bibliothek API client with CLI
Home-page: https://github.com/OskarsMC-Network/papermc-bibliothek
License: MIT
Author: Oskar
Author-email: 56176746+OskarZyg@users.noreply.github.com
Requires-Python: >=3.9,<4.0
Classifier: License :: OSI Approved :: MIT License
Classifier: Programming Language :: Python :: 3
Classifier: Programming Language :: Python :: 3.9
Classifier: Programming Language :: Python :: 3.10
Classifier: Programming Language :: Python :: 3.11
Requires-Dist: python-dateutil (>=2.8.2,<3.0.0)
Requires-Dist: urllib3 (>=2.0.3,<3.0.0)
Project-URL: Repository, https://github.com/OskarsMC-Network/papermc-bibliothek
